ConfocalProjectionPlugin/__init__.py
ConfocalProjectionPlugin/confocal_projection_acquisition.py
ConfocalProjectionPlugin/plugin_config.yml
ConfocalProjectionPlugin/controller/__init__.py
ConfocalProjectionPlugin/controller/confocal_projection_controller.py
ConfocalProjectionPlugin/model/__init__.py
ConfocalProjectionPlugin/model/features/__init__.py
ConfocalProjectionPlugin/model/features/confocal_projection.py
ConfocalProjectionPlugin/view/__init__.py
ConfocalProjectionPlugin/view/confocal_projection_frame.py
navigate_confocal_projection-0.0.2.dist-info/LICENSE
navigate_confocal_projection-0.0.2.dist-info/METADATA
navigate_confocal_projection-0.0.2.dist-info/WHEEL
navigate_confocal_projection-0.0.2.dist-info/entry_points.txt
navigate_confocal_projection-0.0.2.dist-info/top_level.txt
navigate_confocal_projection-0.0.2.dist-info/RECORD
