Metadata-Version: 2.1
Name: navigate-confocal-projection
Version: 0.0.2
Summary: A navigate plugin for high-speed imaging in a projection format.
Author: The Dean Lab, UT Southwestern Medical Center
License: MIT License
Project-URL: Source, https://github.com/TheDeanLab/navigate-confocal_projection
Classifier: Intended Audience :: Developers
Classifier: Operating System :: POSIX :: Linux
Classifier: Operating System :: MacOS :: MacOS X
Classifier: Operating System :: Microsoft :: Windows
Classifier: Programming Language :: Python :: 3.9
Classifier: Programming Language :: Python :: Implementation :: CPython
Classifier: Programming Language :: Python :: Implementation :: PyPy
License-File: LICENSE
